{"74.7": [{"d": "2023-01-01", "v": 0.0}, {"d": "2023-01-08", "v": 0.0}, {"d": "2023-01-15", "v": 0.0}, {"d": "2023-01-22", "v": 0.0}, {"d": "2023-01-29", "v": 0.0}, {"d": "2023-02-05", "v": 0.0}, {"d": "2023-02-12", "v": 0.0}, {"d": "2023-02-19", "v": 0.0}, {"d": "2023-02-26", "v": 0.0}, {"d": "2023-03-05", "v": 0.0}, {"d": "2023-03-12", "v": 0.0}, {"d": "2023-03-19", "v": 0.0}, {"d": "2023-03-26", "v": 0.0}, {"d": "2023-04-02", "v": 0.0}, {"d": "2023-04-09", "v": 0.0}, {"d": "2023-04-16", "v": 0.0}, {"d": "2023-04-23", "v": 0.0}, {"d": "2023-04-30", "v": 0.0}, {"d": "2023-05-07", "v": 0.0}, {"d": "2023-05-14", "v": 0.0}, {"d": "2023-05-21", "v": 0.0}, {"d": "2023-05-28", "v": 0.0}, {"d": "2023-06-04", "v": 0.0}, {"d": "2023-06-11", "v": 0.0}, {"d": "2023-06-18", "v": 0.0}, {"d": "2023-06-25", "v": 0.0}, {"d": "2023-07-02", "v": 0.0}, {"d": "2023-07-09", "v": 0.0}, {"d": "2023-07-16", "v": 0.0}, {"d": "2023-07-23", "v": 0.0}, {"d": "2023-07-30", "v": 0.0}, {"d": "2023-08-06", "v": 0.0}, {"d": "2023-08-13", "v": 0.222}, {"d": "2023-08-20", "v": 4.244}, {"d": "2023-08-27", "v": 0.0}, {"d": "2023-09-03", "v": -0.301}, {"d": "2023-09-10", "v": 6.99}, {"d": "2023-09-17", "v": 0.0}, {"d": "2023-09-24", "v": 0.0}, {"d": "2023-10-01", "v": 0.0}, {"d": "2023-10-08", "v": 0.0}, {"d": "2023-10-15", "v": 0.0}, {"d": "2023-10-22", "v": 0.0}, {"d": "2023-10-29", "v": 0.0}, {"d": "2023-11-05", "v": 0.0}, {"d": "2023-11-12", "v": 0.0}, {"d": "2023-11-19", "v": 0.0}, {"d": "2023-11-26", "v": 0.0}, {"d": "2023-12-03", "v": 0.0}, {"d": "2023-12-10", "v": 0.0}, {"d": "2023-12-17", "v": 0.0}, {"d": "2023-12-24", "v": 0.0}, {"d": "2023-12-31", "v": 0.0}, {"d": "2024-01-01", "v": 0.0}, {"d": "2024-01-08", "v": 0.0}, {"d": "2024-01-15", "v": 0.0}, {"d": "2024-01-22", "v": 0.0}, {"d": "2024-01-29", "v": 0.0}, {"d": "2024-02-05", "v": 0.0}, {"d": "2024-02-12", "v": 0.0}, {"d": "2024-02-19", "v": 0.0}, {"d": "2024-02-26", "v": 0.0}, {"d": "2024-03-04", "v": 0.0}, {"d": "2024-03-11", "v": 0.0}, {"d": "2024-03-18", "v": 0.0}, {"d": "2024-03-26", "v": 0.0}, {"d": "2024-04-02", "v": 0.0}, {"d": "2024-04-09", "v": 0.0}, {"d": "2024-04-16", "v": 0.0}, {"d": "2024-04-23", "v": 0.0}, {"d": "2024-04-30", "v": 0.0}, {"d": "2024-05-07", "v": 0.0}, {"d": "2024-05-14", "v": 0.0}, {"d": "2024-05-21", "v": 0.0}, {"d": "2024-05-28", "v": 0.0}, {"d": "2024-06-04", "v": 0.0}, {"d": "2024-06-11", "v": 0.0}, {"d": "2024-06-18", "v": 0.0}, {"d": "2024-06-25", "v": 0.0}, {"d": "2024-07-02", "v": 6.456}, {"d": "2024-07-09", "v": 0.0}, {"d": "2024-07-16", "v": 0.0}, {"d": "2024-07-23", "v": 9.75}, {"d": "2024-07-30", "v": 0.0}, {"d": "2024-08-06", "v": -6.825}, {"d": "2024-08-13", "v": 8.258}, {"d": "2024-08-20", "v": 0.467}, {"d": "2024-08-27", "v": 0.0}, {"d": "2024-09-03", "v": 0.211}, {"d": "2024-09-10", "v": -3.071}, {"d": "2024-09-17", "v": 0.0}, {"d": "2024-09-24", "v": -4.587}, {"d": "2024-10-01", "v": 0.0}, {"d": "2024-10-08", "v": 0.0}, {"d": "2024-10-15", "v": 0.0}, {"d": "2024-10-22", "v": 0.0}, {"d": "2024-10-29", "v": 0.0}, {"d": "2024-11-05", "v": 0.0}, {"d": "2024-11-12", "v": 0.0}, {"d": "2024-11-19", "v": 0.0}, {"d": "2024-11-26", "v": 0.0}, {"d": "2024-12-03", "v": 0.0}, {"d": "2024-12-10", "v": 0.0}, {"d": "2024-12-17", "v": 0.0}, {"d": "2024-12-24", "v": 0.0}, {"d": "2024-12-31", "v": 0.0}, {"d": "2025-01-01", "v": 0.0}, {"d": "2025-01-08", "v": 0.0}, {"d": "2025-01-15", "v": 0.0}, {"d": "2025-01-22", "v": 0.0}, {"d": "2025-01-29", "v": 0.0}, {"d": "2025-02-05", "v": 0.0}, {"d": "2025-02-12", "v": 0.0}, {"d": "2025-02-19", "v": 0.0}, {"d": "2025-02-26", "v": 0.0}, {"d": "2025-03-05", "v": 0.0}, {"d": "2025-03-12", "v": 0.0}, {"d": "2025-03-19", "v": 0.0}, {"d": "2025-03-26", "v": 0.0}, {"d": "2025-04-02", "v": 0.0}, {"d": "2025-04-09", "v": 0.0}, {"d": "2025-04-17", "v": 0.0}, {"d": "2025-04-24", "v": 0.0}, {"d": "2025-05-01", "v": 0.0}, {"d": "2025-05-08", "v": 0.0}, {"d": "2025-05-15", "v": 0.0}, {"d": "2025-05-22", "v": 0.0}, {"d": "2025-05-29", "v": 0.0}, {"d": "2025-06-05", "v": 0.0}, {"d": "2025-06-12", "v": -3.49}, {"d": "2025-06-19", "v": -3.765}, {"d": "2025-06-26", "v": -6.664}, {"d": "2025-07-03", "v": 6.343}, {"d": "2025-07-10", "v": 8.273}, {"d": "2025-07-17", "v": 0.0}, {"d": "2025-07-24", "v": 0.0}, {"d": "2025-07-31", "v": 0.313}, {"d": "2025-08-07", "v": 1.082}, {"d": "2025-08-14", "v": -1.967}, {"d": "2025-08-21", "v": 0.803}, {"d": "2025-08-28", "v": 3.696}, {"d": "2025-09-04", "v": 4.117}, {"d": "2025-09-11", "v": -3.304}, {"d": "2025-09-18", "v": 0.0}, {"d": "2025-09-25", "v": 0.0}, {"d": "2025-10-02", "v": 0.0}, {"d": "2025-10-09", "v": 0.0}, {"d": "2025-10-16", "v": 0.0}, {"d": "2025-10-23", "v": 0.0}, {"d": "2025-10-31", "v": 0.0}, {"d": "2025-11-07", "v": 0.0}, {"d": "2025-11-14", "v": 0.0}, {"d": "2025-11-21", "v": 0.0}, {"d": "2025-11-28", "v": 0.0}, {"d": "2025-12-05", "v": 1.045}, {"d": "2025-12-12", "v": 0.0}, {"d": "2025-12-19", "v": 0.0}, {"d": "2025-12-26", "v": 0.0}], "75.2": [{"d": "2023-01-01", "v": 0.0}, {"d": "2023-01-08", "v": 0.0}, {"d": "2023-01-15", "v": 0.0}, {"d": "2023-01-22", "v": 0.0}, {"d": "2023-01-29", "v": 0.0}, {"d": "2023-02-05", "v": 0.0}, {"d": "2023-02-12", "v": 0.0}, {"d": "2023-02-19", "v": 0.0}, {"d": "2023-02-26", "v": 0.0}, {"d": "2023-03-05", "v": 0.0}, {"d": "2023-03-12", "v": 0.0}, {"d": "2023-03-19", "v": 0.0}, {"d": "2023-03-26", "v": 0.0}, {"d": "2023-04-02", "v": 0.0}, {"d": "2023-04-09", "v": 0.0}, {"d": "2023-04-16", "v": 0.0}, {"d": "2023-04-23", "v": 0.0}, {"d": "2023-04-30", "v": 0.0}, {"d": "2023-05-07", "v": 0.0}, {"d": "2023-05-14", "v": 0.0}, {"d": "2023-05-21", "v": 0.0}, {"d": "2023-05-28", "v": 0.0}, {"d": "2023-06-04", "v": 0.0}, {"d": "2023-06-11", "v": 0.0}, {"d": "2023-06-18", "v": 0.0}, {"d": "2023-06-25", "v": 0.0}, {"d": "2023-07-02", "v": 0.0}, {"d": "2023-07-09", "v": 0.0}, {"d": "2023-07-16", "v": 0.0}, {"d": "2023-07-23", "v": 0.0}, {"d": "2023-07-30", "v": 0.0}, {"d": "2023-08-06", "v": 0.0}, {"d": "2023-08-13", "v": 0.0}, {"d": "2023-08-20", "v": 12.147}, {"d": "2023-08-27", "v": 0.0}, {"d": "2023-09-03", "v": 0.0}, {"d": "2023-09-10", "v": 0.0}, {"d": "2023-09-17", "v": 0.0}, {"d": "2023-09-24", "v": 0.0}, {"d": "2023-10-01", "v": 0.0}, {"d": "2023-10-08", "v": 0.0}, {"d": "2023-10-15", "v": 0.0}, {"d": "2023-10-22", "v": 0.0}, {"d": "2023-10-29", "v": 0.0}, {"d": "2023-11-05", "v": 0.0}, {"d": "2023-11-12", "v": 0.0}, {"d": "2023-11-19", "v": 0.0}, {"d": "2023-11-26", "v": 0.0}, {"d": "2023-12-03", "v": 0.0}, {"d": "2023-12-10", "v": 0.0}, {"d": "2023-12-17", "v": 0.0}, {"d": "2023-12-24", "v": 0.0}, {"d": "2023-12-31", "v": 0.0}, {"d": "2024-01-01", "v": 0.0}, {"d": "2024-01-08", "v": 0.0}, {"d": "2024-01-15", "v": 0.0}, {"d": "2024-01-22", "v": 0.0}, {"d": "2024-01-29", "v": 0.0}, {"d": "2024-02-05", "v": 0.0}, {"d": "2024-02-12", "v": 0.0}, {"d": "2024-02-19", "v": 0.0}, {"d": "2024-02-26", "v": 0.0}, {"d": "2024-03-04", "v": 0.0}, {"d": "2024-03-11", "v": 0.0}, {"d": "2024-03-18", "v": 0.0}, {"d": "2024-03-26", "v": 0.0}, {"d": "2024-04-02", "v": 0.0}, {"d": "2024-04-09", "v": 0.0}, {"d": "2024-04-16", "v": 0.0}, {"d": "2024-04-23", "v": 0.0}, {"d": "2024-04-30", "v": 0.0}, {"d": "2024-05-07", "v": 0.0}, {"d": "2024-05-14", "v": 0.0}, {"d": "2024-05-21", "v": 0.0}, {"d": "2024-05-28", "v": 0.0}, {"d": "2024-06-04", "v": 0.0}, {"d": "2024-06-11", "v": 0.0}, {"d": "2024-06-18", "v": 0.0}, {"d": "2024-06-25", "v": 0.0}, {"d": "2024-07-02", "v": 0.0}, {"d": "2024-07-09", "v": 0.0}, {"d": "2024-07-16", "v": 0.0}, {"d": "2024-07-23", "v": 0.0}, {"d": "2024-07-30", "v": 0.0}, {"d": "2024-08-06", "v": 0.0}, {"d": "2024-08-13", "v": 0.0}, {"d": "2024-08-20", "v": 0.0}, {"d": "2024-08-27", "v": 0.0}, {"d": "2024-09-03", "v": 0.0}, {"d": "2024-09-10", "v": 0.0}, {"d": "2024-09-17", "v": 0.0}, {"d": "2024-09-24", "v": 0.0}, {"d": "2024-10-01", "v": 0.0}, {"d": "2024-10-08", "v": 0.0}, {"d": "2024-10-15", "v": 0.0}, {"d": "2024-10-22", "v": 0.0}, {"d": "2024-10-29", "v": 0.0}, {"d": "2024-11-05", "v": 0.0}, {"d": "2024-11-12", "v": 0.0}, {"d": "2024-11-19", "v": 0.0}, {"d": "2024-11-26", "v": 0.0}, {"d": "2024-12-03", "v": 0.0}, {"d": "2024-12-10", "v": 0.0}, {"d": "2024-12-17", "v": 0.0}, {"d": "2024-12-24", "v": 0.0}, {"d": "2024-12-31", "v": 0.0}, {"d": "2025-01-01", "v": 0.0}, {"d": "2025-01-08", "v": 0.0}, {"d": "2025-01-15", "v": 0.0}, {"d": "2025-01-22", "v": 0.0}, {"d": "2025-01-29", "v": 0.0}, {"d": "2025-02-05", "v": 0.0}, {"d": "2025-02-12", "v": 0.0}, {"d": "2025-02-19", "v": 0.0}, {"d": "2025-02-26", "v": 0.0}, {"d": "2025-03-05", "v": 0.0}, {"d": "2025-03-12", "v": 0.0}, {"d": "2025-03-19", "v": 0.0}, {"d": "2025-03-26", "v": 0.0}, {"d": "2025-04-02", "v": 0.0}, {"d": "2025-04-09", "v": 0.0}, {"d": "2025-04-17", "v": 0.0}, {"d": "2025-04-24", "v": 0.0}, {"d": "2025-05-01", "v": 0.0}, {"d": "2025-05-08", "v": 0.0}, {"d": "2025-05-15", "v": 0.0}, {"d": "2025-05-22", "v": 0.0}, {"d": "2025-05-29", "v": 0.0}, {"d": "2025-06-05", "v": 0.0}, {"d": "2025-06-12", "v": 0.0}, {"d": "2025-06-19", "v": 0.0}, {"d": "2025-06-26", "v": 0.0}, {"d": "2025-07-03", "v": 0.0}, {"d": "2025-07-10", "v": 0.0}, {"d": "2025-07-17", "v": 0.0}, {"d": "2025-07-24", "v": 0.0}, {"d": "2025-07-31", "v": 0.0}, {"d": "2025-08-07", "v": 0.0}, {"d": "2025-08-14", "v": 0.0}, {"d": "2025-08-21", "v": 0.0}, {"d": "2025-08-28", "v": 0.0}, {"d": "2025-09-04", "v": 0.0}, {"d": "2025-09-11", "v": 0.0}, {"d": "2025-09-18", "v": 0.0}, {"d": "2025-09-25", "v": 0.0}, {"d": "2025-10-02", "v": 0.0}, {"d": "2025-10-09", "v": 0.0}, {"d": "2025-10-16", "v": 0.0}, {"d": "2025-10-23", "v": 0.0}, {"d": "2025-10-31", "v": 0.0}, {"d": "2025-11-07", "v": 0.0}, {"d": "2025-11-14", "v": 0.0}, {"d": "2025-11-21", "v": 0.0}, {"d": "2025-11-28", "v": 0.0}, {"d": "2025-12-05", "v": 2.226}, {"d": "2025-12-12", "v": 1.566}, {"d": "2025-12-19", "v": 1.734}, {"d": "2025-12-26", "v": 0.0}]}