{"year": "2022", "season": "Annual", "count": 625, "data": [{"lat": 37.0, "lon": 68.0, "u": 0.85, "v": 0.0, "speed": 0.85, "dir": 269.9}, {"lat": 37.0, "lon": 69.25, "u": 0.13, "v": 0.43, "speed": 0.45, "dir": 197.1}, {"lat": 37.0, "lon": 70.5, "u": -0.56, "v": 0.25, "speed": 0.62, "dir": 114.3}, {"lat": 37.0, "lon": 71.75, "u": -0.09, "v": 0.08, "speed": 0.12, "dir": 129.8}, {"lat": 37.0, "lon": 73.0, "u": -0.12, "v": 0.05, "speed": 0.13, "dir": 112.0}, {"lat": 37.0, "lon": 74.25, "u": -0.04, "v": 0.55, "speed": 0.55, "dir": 176.2}, {"lat": 37.0, "lon": 75.5, "u": 0.72, "v": 0.94, "speed": 1.18, "dir": 217.2}, {"lat": 37.0, "lon": 76.75, "u": 0.3, "v": 0.47, "speed": 0.56, "dir": 212.2}, {"lat": 37.0, "lon": 78.0, "u": 0.01, "v": 0.44, "speed": 0.44, "dir": 181.0}, {"lat": 37.0, "lon": 79.25, "u": 0.23, "v": 0.01, "speed": 0.23, "dir": 266.6}, {"lat": 37.0, "lon": 80.5, "u": 0.32, "v": -0.11, "speed": 0.34, "dir": 288.9}, {"lat": 37.0, "lon": 81.75, "u": 0.29, "v": 0.22, "speed": 0.37, "dir": 232.3}, {"lat": 37.0, "lon": 83.0, "u": -0.03, "v": 0.42, "speed": 0.42, "dir": 175.7}, {"lat": 37.0, "lon": 84.25, "u": -0.18, "v": 0.36, "speed": 0.4, "dir": 153.8}, {"lat": 37.0, "lon": 85.5, "u": 0.01, "v": 0.16, "speed": 0.16, "dir": 184.7}, {"lat": 37.0, "lon": 86.75, "u": 1.37, "v": 0.04, "speed": 1.37, "dir": 268.4}, {"lat": 37.0, "lon": 88.0, "u": 1.72, "v": 0.18, "speed": 1.73, "dir": 263.9}, {"lat": 37.0, "lon": 89.25, "u": 1.54, "v": 0.41, "speed": 1.6, "dir": 255.1}, {"lat": 37.0, "lon": 90.5, "u": 0.33, "v": 0.74, "speed": 0.81, "dir": 204.0}, {"lat": 37.0, "lon": 91.75, "u": 0.98, "v": -0.51, "speed": 1.1, "dir": 297.4}, {"lat": 37.0, "lon": 93.0, "u": 1.17, "v": -0.57, "speed": 1.3, "dir": 295.9}, {"lat": 37.0, "lon": 94.25, "u": 1.85, "v": -1.34, "speed": 2.28, "dir": 305.8}, {"lat": 37.0, "lon": 95.5, "u": 2.11, "v": -1.03, "speed": 2.35, "dir": 296.0}, {"lat": 37.0, "lon": 96.75, "u": 1.6, "v": -0.05, "speed": 1.6, "dir": 271.9}, {"lat": 37.0, "lon": 98.0, "u": 0.58, "v": 0.08, "speed": 0.59, "dir": 262.2}, {"lat": 35.75, "lon": 68.0, "u": 0.17, "v": 0.07, "speed": 0.19, "dir": 247.8}, {"lat": 35.75, "lon": 69.25, "u": -0.31, "v": -0.03, "speed": 0.31, "dir": 84.1}, {"lat": 35.75, "lon": 70.5, "u": 0.07, "v": -0.05, "speed": 0.08, "dir": 307.6}, {"lat": 35.75, "lon": 71.75, "u": 0.05, "v": -0.37, "speed": 0.38, "dir": 352.3}, {"lat": 35.75, "lon": 73.0, "u": 0.29, "v": -0.69, "speed": 0.75, "dir": 337.0}, {"lat": 35.75, "lon": 74.25, "u": 0.29, "v": -0.21, "speed": 0.36, "dir": 306.3}, {"lat": 35.75, "lon": 75.5, "u": -0.12, "v": -0.5, "speed": 0.52, "dir": 13.9}, {"lat": 35.75, "lon": 76.75, "u": -0.18, "v": 0.36, "speed": 0.4, "dir": 154.0}, {"lat": 35.75, "lon": 78.0, "u": 0.61, "v": 1.71, "speed": 1.82, "dir": 199.7}, {"lat": 35.75, "lon": 79.25, "u": 0.03, "v": -0.08, "speed": 0.08, "dir": 340.8}, {"lat": 35.75, "lon": 80.5, "u": 0.23, "v": 0.79, "speed": 0.82, "dir": 196.5}, {"lat": 35.75, "lon": 81.75, "u": 0.37, "v": 0.53, "speed": 0.65, "dir": 215.0}, {"lat": 35.75, "lon": 83.0, "u": 1.11, "v": 0.24, "speed": 1.14, "dir": 257.8}, {"lat": 35.75, "lon": 84.25, "u": 1.51, "v": -0.53, "speed": 1.6, "dir": 289.3}, {"lat": 35.75, "lon": 85.5, "u": 1.34, "v": 0.19, "speed": 1.35, "dir": 261.9}, {"lat": 35.75, "lon": 86.75, "u": 1.94, "v": -0.22, "speed": 1.95, "dir": 276.4}, {"lat": 35.75, "lon": 88.0, "u": 1.71, "v": -0.06, "speed": 1.71, "dir": 272.1}, {"lat": 35.75, "lon": 89.25, "u": 1.15, "v": 0.09, "speed": 1.15, "dir": 265.6}, {"lat": 35.75, "lon": 90.5, "u": 1.05, "v": -0.14, "speed": 1.06, "dir": 277.8}, {"lat": 35.75, "lon": 91.75, "u": 1.38, "v": -0.22, "speed": 1.39, "dir": 278.9}, {"lat": 35.75, "lon": 93.0, "u": 1.2, "v": -0.79, "speed": 1.43, "dir": 303.5}, {"lat": 35.75, "lon": 94.25, "u": 0.28, "v": -0.13, "speed": 0.31, "dir": 293.8}, {"lat": 35.75, "lon": 95.5, "u": 0.97, "v": -0.41, "speed": 1.05, "dir": 292.9}, {"lat": 35.75, "lon": 96.75, "u": 0.48, "v": -0.26, "speed": 0.55, "dir": 298.2}, {"lat": 35.75, "lon": 98.0, "u": 0.45, "v": -0.18, "speed": 0.48, "dir": 292.2}, {"lat": 34.5, "lon": 68.0, "u": 0.42, "v": -0.92, "speed": 1.01, "dir": 335.3}, {"lat": 34.5, "lon": 69.25, "u": 0.1, "v": -0.07, "speed": 0.12, "dir": 306.6}, {"lat": 34.5, "lon": 70.5, "u": 0.28, "v": 0.03, "speed": 0.29, "dir": 264.5}, {"lat": 34.5, "lon": 71.75, "u": 0.11, "v": -0.72, "speed": 0.73, "dir": 351.5}, {"lat": 34.5, "lon": 73.0, "u": -0.58, "v": -0.65, "speed": 0.87, "dir": 41.9}, {"lat": 34.5, "lon": 74.25, "u": 0.31, "v": -0.71, "speed": 0.78, "dir": 336.3}, {"lat": 34.5, "lon": 75.5, "u": 0.04, "v": 0.24, "speed": 0.24, "dir": 190.1}, {"lat": 34.5, "lon": 76.75, "u": -0.28, "v": -0.16, "speed": 0.32, "dir": 60.5}, {"lat": 34.5, "lon": 78.0, "u": -0.22, "v": -0.26, "speed": 0.35, "dir": 40.2}, {"lat": 34.5, "lon": 79.25, "u": 1.44, "v": 1.2, "speed": 1.87, "dir": 230.2}, {"lat": 34.5, "lon": 80.5, "u": 0.94, "v": 0.73, "speed": 1.19, "dir": 232.0}, {"lat": 34.5, "lon": 81.75, "u": 0.95, "v": 0.73, "speed": 1.19, "dir": 232.4}, {"lat": 34.5, "lon": 83.0, "u": 1.44, "v": 0.43, "speed": 1.5, "dir": 253.4}, {"lat": 34.5, "lon": 84.25, "u": 1.45, "v": 0.26, "speed": 1.47, "dir": 259.7}, {"lat": 34.5, "lon": 85.5, "u": 1.08, "v": 0.42, "speed": 1.16, "dir": 248.9}, {"lat": 34.5, "lon": 86.75, "u": 2.09, "v": 0.43, "speed": 2.13, "dir": 258.3}, {"lat": 34.5, "lon": 88.0, "u": 2.07, "v": 0.28, "speed": 2.09, "dir": 262.4}, {"lat": 34.5, "lon": 89.25, "u": 1.43, "v": 0.35, "speed": 1.47, "dir": 256.2}, {"lat": 34.5, "lon": 90.5, "u": 2.25, "v": 0.72, "speed": 2.37, "dir": 252.4}, {"lat": 34.5, "lon": 91.75, "u": 1.86, "v": -0.48, "speed": 1.92, "dir": 284.4}, {"lat": 34.5, "lon": 93.0, "u": 1.41, "v": -0.41, "speed": 1.47, "dir": 286.1}, {"lat": 34.5, "lon": 94.25, "u": 1.07, "v": 0.19, "speed": 1.09, "dir": 260.1}, {"lat": 34.5, "lon": 95.5, "u": 0.97, "v": -0.03, "speed": 0.97, "dir": 271.9}, {"lat": 34.5, "lon": 96.75, "u": 1.2, "v": 0.11, "speed": 1.21, "dir": 264.8}, {"lat": 34.5, "lon": 98.0, "u": 1.43, "v": 0.07, "speed": 1.43, "dir": 267.3}, {"lat": 33.25, "lon": 68.0, "u": 0.64, "v": -0.08, "speed": 0.65, "dir": 276.8}, {"lat": 33.25, "lon": 69.25, "u": 0.23, "v": -0.06, "speed": 0.24, "dir": 284.9}, {"lat": 33.25, "lon": 70.5, "u": 0.02, "v": -0.43, "speed": 0.43, "dir": 357.2}, {"lat": 33.25, "lon": 71.75, "u": -0.04, "v": -0.34, "speed": 0.35, "dir": 6.8}, {"lat": 33.25, "lon": 73.0, "u": 0.2, "v": -0.39, "speed": 0.43, "dir": 333.0}, {"lat": 33.25, "lon": 74.25, "u": -0.06, "v": -0.24, "speed": 0.25, "dir": 13.3}, {"lat": 33.25, "lon": 75.5, "u": -0.31, "v": -0.8, "speed": 0.86, "dir": 21.3}, {"lat": 33.25, "lon": 76.75, "u": -0.3, "v": 0.49, "speed": 0.58, "dir": 149.0}, {"lat": 33.25, "lon": 78.0, "u": 0.34, "v": 0.59, "speed": 0.68, "dir": 210.2}, {"lat": 33.25, "lon": 79.25, "u": 0.97, "v": 0.42, "speed": 1.05, "dir": 246.4}, {"lat": 33.25, "lon": 80.5, "u": 0.89, "v": -0.11, "speed": 0.9, "dir": 277.4}, {"lat": 33.25, "lon": 81.75, "u": 1.11, "v": -0.09, "speed": 1.11, "dir": 274.6}, {"lat": 33.25, "lon": 83.0, "u": 1.18, "v": 0.02, "speed": 1.18, "dir": 269.2}, {"lat": 33.25, "lon": 84.25, "u": 0.78, "v": 0.35, "speed": 0.85, "dir": 245.9}, {"lat": 33.25, "lon": 85.5, "u": 1.56, "v": 0.26, "speed": 1.59, "dir": 260.4}, {"lat": 33.25, "lon": 86.75, "u": 1.28, "v": -0.03, "speed": 1.28, "dir": 271.5}, {"lat": 33.25, "lon": 88.0, "u": 1.5, "v": -0.1, "speed": 1.5, "dir": 274.0}, {"lat": 33.25, "lon": 89.25, "u": 1.62, "v": -0.12, "speed": 1.62, "dir": 274.2}, {"lat": 33.25, "lon": 90.5, "u": 1.05, "v": 0.29, "speed": 1.08, "dir": 254.7}, {"lat": 33.25, "lon": 91.75, "u": 1.45, "v": 0.72, "speed": 1.62, "dir": 243.5}, {"lat": 33.25, "lon": 93.0, "u": 1.65, "v": 0.32, "speed": 1.68, "dir": 258.9}, {"lat": 33.25, "lon": 94.25, "u": 0.86, "v": 0.98, "speed": 1.3, "dir": 221.2}, {"lat": 33.25, "lon": 95.5, "u": 0.84, "v": 0.15, "speed": 0.85, "dir": 259.6}, {"lat": 33.25, "lon": 96.75, "u": 0.69, "v": 0.25, "speed": 0.73, "dir": 250.3}, {"lat": 33.25, "lon": 98.0, "u": 0.62, "v": 0.01, "speed": 0.62, "dir": 269.2}, {"lat": 32.0, "lon": 68.0, "u": 1.62, "v": -0.06, "speed": 1.62, "dir": 272.1}, {"lat": 32.0, "lon": 69.25, "u": 0.28, "v": -0.23, "speed": 0.36, "dir": 309.0}, {"lat": 32.0, "lon": 70.5, "u": 0.12, "v": -0.35, "speed": 0.37, "dir": 341.3}, {"lat": 32.0, "lon": 71.75, "u": -0.53, "v": -0.57, "speed": 0.78, "dir": 42.9}, {"lat": 32.0, "lon": 73.0, "u": -0.32, "v": -0.11, "speed": 0.33, "dir": 71.6}, {"lat": 32.0, "lon": 74.25, "u": -0.01, "v": -0.37, "speed": 0.37, "dir": 2.2}, {"lat": 32.0, "lon": 75.5, "u": -0.26, "v": -0.15, "speed": 0.3, "dir": 59.7}, {"lat": 32.0, "lon": 76.75, "u": 0.0, "v": -0.54, "speed": 0.54, "dir": 359.8}, {"lat": 32.0, "lon": 78.0, "u": 0.49, "v": -0.15, "speed": 0.51, "dir": 287.1}, {"lat": 32.0, "lon": 79.25, "u": 1.05, "v": 0.04, "speed": 1.05, "dir": 267.9}, {"lat": 32.0, "lon": 80.5, "u": 1.23, "v": 1.03, "speed": 1.6, "dir": 230.0}, {"lat": 32.0, "lon": 81.75, "u": 2.02, "v": 1.28, "speed": 2.39, "dir": 237.8}, {"lat": 32.0, "lon": 83.0, "u": 1.37, "v": 1.01, "speed": 1.71, "dir": 233.6}, {"lat": 32.0, "lon": 84.25, "u": 1.14, "v": 0.34, "speed": 1.18, "dir": 253.4}, {"lat": 32.0, "lon": 85.5, "u": 1.45, "v": 0.46, "speed": 1.52, "dir": 252.3}, {"lat": 32.0, "lon": 86.75, "u": 1.44, "v": 0.01, "speed": 1.44, "dir": 269.5}, {"lat": 32.0, "lon": 88.0, "u": 1.61, "v": -0.1, "speed": 1.62, "dir": 273.6}, {"lat": 32.0, "lon": 89.25, "u": 1.6, "v": -0.23, "speed": 1.62, "dir": 278.2}, {"lat": 32.0, "lon": 90.5, "u": 1.3, "v": 0.26, "speed": 1.33, "dir": 258.6}, {"lat": 32.0, "lon": 91.75, "u": 0.76, "v": 0.15, "speed": 0.78, "dir": 259.2}, {"lat": 32.0, "lon": 93.0, "u": -0.72, "v": -0.14, "speed": 0.74, "dir": 79.1}, {"lat": 32.0, "lon": 94.25, "u": -0.57, "v": -0.08, "speed": 0.57, "dir": 81.5}, {"lat": 32.0, "lon": 95.5, "u": 0.94, "v": 1.07, "speed": 1.42, "dir": 221.5}, {"lat": 32.0, "lon": 96.75, "u": 0.36, "v": 0.34, "speed": 0.5, "dir": 226.7}, {"lat": 32.0, "lon": 98.0, "u": 0.54, "v": 0.1, "speed": 0.55, "dir": 260.0}, {"lat": 30.75, "lon": 68.0, "u": 1.54, "v": -0.07, "speed": 1.54, "dir": 272.5}, {"lat": 30.75, "lon": 69.25, "u": 0.59, "v": 0.0, "speed": 0.59, "dir": 269.9}, {"lat": 30.75, "lon": 70.5, "u": 0.05, "v": -0.48, "speed": 0.49, "dir": 353.7}, {"lat": 30.75, "lon": 71.75, "u": -0.43, "v": 0.28, "speed": 0.51, "dir": 123.0}, {"lat": 30.75, "lon": 73.0, "u": -0.28, "v": 0.26, "speed": 0.38, "dir": 133.0}, {"lat": 30.75, "lon": 74.25, "u": -0.03, "v": -0.02, "speed": 0.04, "dir": 50.4}, {"lat": 30.75, "lon": 75.5, "u": -0.05, "v": -0.27, "speed": 0.27, "dir": 9.9}, {"lat": 30.75, "lon": 76.75, "u": 0.13, "v": -0.6, "speed": 0.61, "dir": 347.4}, {"lat": 30.75, "lon": 78.0, "u": 0.26, "v": -0.24, "speed": 0.35, "dir": 313.3}, {"lat": 30.75, "lon": 79.25, "u": -0.07, "v": -0.42, "speed": 0.42, "dir": 9.7}, {"lat": 30.75, "lon": 80.5, "u": 0.47, "v": 2.08, "speed": 2.14, "dir": 192.8}, {"lat": 30.75, "lon": 81.75, "u": -0.03, "v": 0.74, "speed": 0.74, "dir": 177.6}, {"lat": 30.75, "lon": 83.0, "u": 1.04, "v": 1.44, "speed": 1.78, "dir": 215.8}, {"lat": 30.75, "lon": 84.25, "u": 1.86, "v": 1.91, "speed": 2.67, "dir": 224.2}, {"lat": 30.75, "lon": 85.5, "u": 1.72, "v": 0.91, "speed": 1.95, "dir": 242.1}, {"lat": 30.75, "lon": 86.75, "u": 1.52, "v": 0.72, "speed": 1.68, "dir": 244.7}, {"lat": 30.75, "lon": 88.0, "u": 2.01, "v": 0.98, "speed": 2.24, "dir": 244.1}, {"lat": 30.75, "lon": 89.25, "u": 1.64, "v": 1.09, "speed": 1.97, "dir": 236.4}, {"lat": 30.75, "lon": 90.5, "u": 1.47, "v": 1.36, "speed": 2.0, "dir": 227.3}, {"lat": 30.75, "lon": 91.75, "u": 0.49, "v": 1.0, "speed": 1.11, "dir": 206.1}, {"lat": 30.75, "lon": 93.0, "u": -0.08, "v": 1.54, "speed": 1.54, "dir": 176.9}, {"lat": 30.75, "lon": 94.25, "u": 0.13, "v": 0.57, "speed": 0.59, "dir": 192.5}, {"lat": 30.75, "lon": 95.5, "u": 0.2, "v": 1.16, "speed": 1.18, "dir": 189.8}, {"lat": 30.75, "lon": 96.75, "u": 0.44, "v": 1.01, "speed": 1.1, "dir": 203.6}, {"lat": 30.75, "lon": 98.0, "u": 0.33, "v": 0.62, "speed": 0.7, "dir": 208.0}, {"lat": 29.5, "lon": 68.0, "u": -0.04, "v": -0.18, "speed": 0.19, "dir": 12.8}, {"lat": 29.5, "lon": 69.25, "u": 0.3, "v": 0.05, "speed": 0.31, "dir": 261.5}, {"lat": 29.5, "lon": 70.5, "u": -0.16, "v": -0.11, "speed": 0.19, "dir": 55.4}, {"lat": 29.5, "lon": 71.75, "u": -0.05, "v": 0.38, "speed": 0.38, "dir": 173.1}, {"lat": 29.5, "lon": 73.0, "u": -0.26, "v": 0.19, "speed": 0.32, "dir": 125.8}, {"lat": 29.5, "lon": 74.25, "u": 0.01, "v": -0.19, "speed": 0.19, "dir": 356.2}, {"lat": 29.5, "lon": 75.5, "u": -0.04, "v": -0.34, "speed": 0.34, "dir": 6.0}, {"lat": 29.5, "lon": 76.75, "u": 0.14, "v": -0.45, "speed": 0.47, "dir": 343.0}, {"lat": 29.5, "lon": 78.0, "u": 0.23, "v": -0.09, "speed": 0.24, "dir": 291.7}, {"lat": 29.5, "lon": 79.25, "u": 0.18, "v": -0.25, "speed": 0.31, "dir": 323.1}, {"lat": 29.5, "lon": 80.5, "u": 0.03, "v": 0.04, "speed": 0.05, "dir": 214.6}, {"lat": 29.5, "lon": 81.75, "u": 0.27, "v": 0.04, "speed": 0.27, "dir": 261.2}, {"lat": 29.5, "lon": 83.0, "u": 0.34, "v": 0.25, "speed": 0.42, "dir": 233.9}, {"lat": 29.5, "lon": 84.25, "u": 0.62, "v": 0.33, "speed": 0.7, "dir": 242.0}, {"lat": 29.5, "lon": 85.5, "u": 0.88, "v": 0.64, "speed": 1.09, "dir": 234.0}, {"lat": 29.5, "lon": 86.75, "u": 1.65, "v": 0.63, "speed": 1.77, "dir": 249.1}, {"lat": 29.5, "lon": 88.0, "u": 1.03, "v": 0.91, "speed": 1.37, "dir": 228.8}, {"lat": 29.5, "lon": 89.25, "u": 0.22, "v": 0.89, "speed": 0.92, "dir": 193.9}, {"lat": 29.5, "lon": 90.5, "u": 0.57, "v": 0.44, "speed": 0.72, "dir": 232.5}, {"lat": 29.5, "lon": 91.75, "u": -0.57, "v": 0.68, "speed": 0.89, "dir": 140.2}, {"lat": 29.5, "lon": 93.0, "u": -0.21, "v": 0.85, "speed": 0.87, "dir": 166.3}, {"lat": 29.5, "lon": 94.25, "u": -0.26, "v": 0.55, "speed": 0.61, "dir": 154.8}, {"lat": 29.5, "lon": 95.5, "u": -0.42, "v": 0.14, "speed": 0.44, "dir": 108.1}, {"lat": 29.5, "lon": 96.75, "u": -0.09, "v": 0.14, "speed": 0.17, "dir": 146.8}, {"lat": 29.5, "lon": 98.0, "u": 0.42, "v": 0.8, "speed": 0.91, "dir": 208.0}, {"lat": 28.25, "lon": 68.0, "u": -0.24, "v": -0.06, "speed": 0.25, "dir": 75.7}, {"lat": 28.25, "lon": 69.25, "u": -0.5, "v": 0.2, "speed": 0.53, "dir": 111.7}, {"lat": 28.25, "lon": 70.5, "u": 0.32, "v": 0.34, "speed": 0.47, "dir": 223.7}, {"lat": 28.25, "lon": 71.75, "u": 0.42, "v": 0.62, "speed": 0.74, "dir": 214.3}, {"lat": 28.25, "lon": 73.0, "u": 0.35, "v": 0.66, "speed": 0.75, "dir": 208.2}, {"lat": 28.25, "lon": 74.25, "u": 0.45, "v": 0.43, "speed": 0.62, "dir": 226.5}, {"lat": 28.25, "lon": 75.5, "u": 0.71, "v": 0.14, "speed": 0.72, "dir": 259.2}, {"lat": 28.25, "lon": 76.75, "u": 0.51, "v": -0.21, "speed": 0.55, "dir": 292.3}, {"lat": 28.25, "lon": 78.0, "u": 0.08, "v": -0.35, "speed": 0.36, "dir": 347.8}, {"lat": 28.25, "lon": 79.25, "u": 0.3, "v": -0.29, "speed": 0.42, "dir": 314.2}, {"lat": 28.25, "lon": 80.5, "u": -0.15, "v": -0.14, "speed": 0.2, "dir": 46.1}, {"lat": 28.25, "lon": 81.75, "u": -0.03, "v": -0.12, "speed": 0.13, "dir": 14.9}, {"lat": 28.25, "lon": 83.0, "u": 0.09, "v": 0.35, "speed": 0.36, "dir": 194.8}, {"lat": 28.25, "lon": 84.25, "u": 0.07, "v": 0.35, "speed": 0.36, "dir": 191.6}, {"lat": 28.25, "lon": 85.5, "u": -0.09, "v": -0.19, "speed": 0.21, "dir": 26.1}, {"lat": 28.25, "lon": 86.75, "u": 0.88, "v": 1.49, "speed": 1.73, "dir": 210.7}, {"lat": 28.25, "lon": 88.0, "u": 0.68, "v": 0.91, "speed": 1.13, "dir": 216.6}, {"lat": 28.25, "lon": 89.25, "u": 0.05, "v": 1.75, "speed": 1.75, "dir": 181.5}, {"lat": 28.25, "lon": 90.5, "u": 0.45, "v": 0.92, "speed": 1.02, "dir": 205.9}, {"lat": 28.25, "lon": 91.75, "u": 0.59, "v": 1.21, "speed": 1.35, "dir": 206.1}, {"lat": 28.25, "lon": 93.0, "u": -0.27, "v": 0.14, "speed": 0.3, "dir": 118.2}, {"lat": 28.25, "lon": 94.25, "u": -0.26, "v": -0.05, "speed": 0.26, "dir": 79.3}, {"lat": 28.25, "lon": 95.5, "u": -0.13, "v": -0.2, "speed": 0.24, "dir": 32.6}, {"lat": 28.25, "lon": 96.75, "u": -0.12, "v": 0.01, "speed": 0.12, "dir": 96.6}, {"lat": 28.25, "lon": 98.0, "u": 0.26, "v": 0.34, "speed": 0.43, "dir": 217.5}, {"lat": 27.0, "lon": 68.0, "u": -0.12, "v": 0.3, "speed": 0.32, "dir": 158.5}, {"lat": 27.0, "lon": 69.25, "u": 0.3, "v": 1.08, "speed": 1.12, "dir": 195.6}, {"lat": 27.0, "lon": 70.5, "u": 0.55, "v": 1.41, "speed": 1.51, "dir": 201.4}, {"lat": 27.0, "lon": 71.75, "u": 0.94, "v": 1.01, "speed": 1.38, "dir": 223.1}, {"lat": 27.0, "lon": 73.0, "u": 0.76, "v": 0.91, "speed": 1.18, "dir": 219.9}, {"lat": 27.0, "lon": 74.25, "u": 0.68, "v": 0.62, "speed": 0.92, "dir": 227.6}, {"lat": 27.0, "lon": 75.5, "u": 0.66, "v": -0.41, "speed": 0.78, "dir": 302.2}, {"lat": 27.0, "lon": 76.75, "u": 0.7, "v": -0.25, "speed": 0.75, "dir": 289.9}, {"lat": 27.0, "lon": 78.0, "u": 0.34, "v": -0.29, "speed": 0.45, "dir": 310.8}, {"lat": 27.0, "lon": 79.25, "u": 0.27, "v": -0.32, "speed": 0.42, "dir": 319.5}, {"lat": 27.0, "lon": 80.5, "u": 0.18, "v": -0.2, "speed": 0.27, "dir": 317.2}, {"lat": 27.0, "lon": 81.75, "u": -0.22, "v": -0.06, "speed": 0.23, "dir": 75.2}, {"lat": 27.0, "lon": 83.0, "u": -0.64, "v": 0.04, "speed": 0.64, "dir": 93.1}, {"lat": 27.0, "lon": 84.25, "u": -0.8, "v": -0.05, "speed": 0.8, "dir": 86.1}, {"lat": 27.0, "lon": 85.5, "u": -0.62, "v": 0.07, "speed": 0.62, "dir": 96.9}, {"lat": 27.0, "lon": 86.75, "u": -0.22, "v": 0.18, "speed": 0.29, "dir": 129.0}, {"lat": 27.0, "lon": 88.0, "u": -0.04, "v": 0.2, "speed": 0.21, "dir": 167.6}, {"lat": 27.0, "lon": 89.25, "u": -0.14, "v": 0.41, "speed": 0.43, "dir": 161.5}, {"lat": 27.0, "lon": 90.5, "u": -0.04, "v": 0.04, "speed": 0.06, "dir": 135.2}, {"lat": 27.0, "lon": 91.75, "u": 0.11, "v": 0.06, "speed": 0.12, "dir": 242.2}, {"lat": 27.0, "lon": 93.0, "u": -0.28, "v": -0.08, "speed": 0.3, "dir": 73.6}, {"lat": 27.0, "lon": 94.25, "u": -0.09, "v": -0.35, "speed": 0.36, "dir": 13.8}, {"lat": 27.0, "lon": 95.5, "u": -0.1, "v": 0.02, "speed": 0.11, "dir": 103.5}, {"lat": 27.0, "lon": 96.75, "u": -0.24, "v": 0.02, "speed": 0.24, "dir": 94.5}, {"lat": 27.0, "lon": 98.0, "u": -0.2, "v": 0.04, "speed": 0.2, "dir": 102.3}, {"lat": 25.75, "lon": 68.0, "u": 2.0, "v": 0.56, "speed": 2.08, "dir": 254.3}, {"lat": 25.75, "lon": 69.25, "u": 1.48, "v": 1.19, "speed": 1.9, "dir": 231.1}, {"lat": 25.75, "lon": 70.5, "u": 1.11, "v": 1.14, "speed": 1.59, "dir": 224.3}, {"lat": 25.75, "lon": 71.75, "u": 1.03, "v": 0.85, "speed": 1.33, "dir": 230.5}, {"lat": 25.75, "lon": 73.0, "u": 0.77, "v": 0.91, "speed": 1.19, "dir": 220.0}, {"lat": 25.75, "lon": 74.25, "u": 1.27, "v": 0.13, "speed": 1.28, "dir": 264.1}, {"lat": 25.75, "lon": 75.5, "u": 0.78, "v": -0.23, "speed": 0.81, "dir": 286.3}, {"lat": 25.75, "lon": 76.75, "u": 0.2, "v": 0.0, "speed": 0.2, "dir": 269.9}, {"lat": 25.75, "lon": 78.0, "u": 0.91, "v": -0.37, "speed": 0.98, "dir": 292.2}, {"lat": 25.75, "lon": 79.25, "u": 0.44, "v": -0.39, "speed": 0.59, "dir": 311.7}, {"lat": 25.75, "lon": 80.5, "u": 0.16, "v": -0.34, "speed": 0.38, "dir": 335.0}, {"lat": 25.75, "lon": 81.75, "u": 0.08, "v": -0.22, "speed": 0.24, "dir": 340.0}, {"lat": 25.75, "lon": 83.0, "u": -0.06, "v": -0.14, "speed": 0.15, "dir": 24.0}, {"lat": 25.75, "lon": 84.25, "u": -0.43, "v": -0.07, "speed": 0.44, "dir": 80.4}, {"lat": 25.75, "lon": 85.5, "u": -0.7, "v": -0.07, "speed": 0.7, "dir": 84.0}, {"lat": 25.75, "lon": 86.75, "u": -0.74, "v": -0.04, "speed": 0.74, "dir": 86.8}, {"lat": 25.75, "lon": 88.0, "u": -0.72, "v": -0.08, "speed": 0.73, "dir": 84.1}, {"lat": 25.75, "lon": 89.25, "u": -0.63, "v": 0.13, "speed": 0.64, "dir": 102.0}, {"lat": 25.75, "lon": 90.5, "u": -0.23, "v": 0.65, "speed": 0.69, "dir": 160.7}, {"lat": 25.75, "lon": 91.75, "u": -0.12, "v": 0.14, "speed": 0.18, "dir": 139.1}, {"lat": 25.75, "lon": 93.0, "u": -0.11, "v": 0.39, "speed": 0.41, "dir": 164.6}, {"lat": 25.75, "lon": 94.25, "u": 0.14, "v": 0.11, "speed": 0.17, "dir": 232.8}, {"lat": 25.75, "lon": 95.5, "u": -0.07, "v": -0.19, "speed": 0.2, "dir": 18.8}, {"lat": 25.75, "lon": 96.75, "u": -0.3, "v": -0.14, "speed": 0.33, "dir": 64.8}, {"lat": 25.75, "lon": 98.0, "u": -0.11, "v": 0.15, "speed": 0.18, "dir": 144.3}, {"lat": 24.5, "lon": 68.0, "u": 2.27, "v": 0.06, "speed": 2.27, "dir": 268.4}, {"lat": 24.5, "lon": 69.25, "u": 2.46, "v": 0.45, "speed": 2.5, "dir": 259.7}, {"lat": 24.5, "lon": 70.5, "u": 1.88, "v": 0.66, "speed": 1.99, "dir": 250.7}, {"lat": 24.5, "lon": 71.75, "u": 0.82, "v": 0.67, "speed": 1.06, "dir": 230.7}, {"lat": 24.5, "lon": 73.0, "u": 0.45, "v": 0.24, "speed": 0.51, "dir": 242.5}, {"lat": 24.5, "lon": 74.25, "u": 0.66, "v": 0.11, "speed": 0.67, "dir": 260.3}, {"lat": 24.5, "lon": 75.5, "u": 0.85, "v": -0.2, "speed": 0.87, "dir": 283.4}, {"lat": 24.5, "lon": 76.75, "u": 0.43, "v": -0.28, "speed": 0.51, "dir": 303.7}, {"lat": 24.5, "lon": 78.0, "u": 0.66, "v": -0.62, "speed": 0.91, "dir": 313.3}, {"lat": 24.5, "lon": 79.25, "u": 0.41, "v": -0.39, "speed": 0.56, "dir": 313.6}, {"lat": 24.5, "lon": 80.5, "u": 0.34, "v": -0.28, "speed": 0.44, "dir": 310.3}, {"lat": 24.5, "lon": 81.75, "u": 0.24, "v": -0.22, "speed": 0.33, "dir": 313.2}, {"lat": 24.5, "lon": 83.0, "u": 0.23, "v": -0.27, "speed": 0.35, "dir": 318.7}, {"lat": 24.5, "lon": 84.25, "u": 0.05, "v": -0.05, "speed": 0.07, "dir": 315.8}, {"lat": 24.5, "lon": 85.5, "u": 0.03, "v": 0.27, "speed": 0.27, "dir": 185.5}, {"lat": 24.5, "lon": 86.75, "u": -0.14, "v": 0.17, "speed": 0.22, "dir": 141.0}, {"lat": 24.5, "lon": 88.0, "u": -0.36, "v": 0.19, "speed": 0.41, "dir": 117.9}, {"lat": 24.5, "lon": 89.25, "u": -0.35, "v": 0.49, "speed": 0.6, "dir": 144.2}, {"lat": 24.5, "lon": 90.5, "u": -0.27, "v": 0.45, "speed": 0.53, "dir": 149.4}, {"lat": 24.5, "lon": 91.75, "u": -0.39, "v": 0.17, "speed": 0.42, "dir": 113.2}, {"lat": 24.5, "lon": 93.0, "u": -0.17, "v": 0.17, "speed": 0.24, "dir": 135.1}, {"lat": 24.5, "lon": 94.25, "u": 0.45, "v": -0.21, "speed": 0.49, "dir": 295.1}, {"lat": 24.5, "lon": 95.5, "u": -0.18, "v": 0.09, "speed": 0.21, "dir": 117.2}, {"lat": 24.5, "lon": 96.75, "u": -0.16, "v": -0.42, "speed": 0.45, "dir": 20.6}, {"lat": 24.5, "lon": 98.0, "u": 0.45, "v": -0.11, "speed": 0.47, "dir": 283.7}, {"lat": 23.25, "lon": 68.0, "u": 3.44, "v": -0.33, "speed": 3.45, "dir": 275.5}, {"lat": 23.25, "lon": 69.25, "u": 2.39, "v": 0.07, "speed": 2.39, "dir": 268.3}, {"lat": 23.25, "lon": 70.5, "u": 1.89, "v": 0.23, "speed": 1.91, "dir": 263.1}, {"lat": 23.25, "lon": 71.75, "u": 1.33, "v": -0.03, "speed": 1.33, "dir": 271.2}, {"lat": 23.25, "lon": 73.0, "u": 0.65, "v": -0.06, "speed": 0.65, "dir": 275.4}, {"lat": 23.25, "lon": 74.25, "u": 0.97, "v": 0.32, "speed": 1.02, "dir": 251.5}, {"lat": 23.25, "lon": 75.5, "u": 1.17, "v": -0.2, "speed": 1.19, "dir": 279.9}, {"lat": 23.25, "lon": 76.75, "u": 0.71, "v": -0.58, "speed": 0.91, "dir": 309.5}, {"lat": 23.25, "lon": 78.0, "u": 0.57, "v": -0.65, "speed": 0.87, "dir": 318.9}, {"lat": 23.25, "lon": 79.25, "u": 0.44, "v": -0.41, "speed": 0.6, "dir": 313.1}, {"lat": 23.25, "lon": 80.5, "u": 0.21, "v": -0.25, "speed": 0.33, "dir": 319.8}, {"lat": 23.25, "lon": 81.75, "u": 0.43, "v": -0.22, "speed": 0.48, "dir": 297.6}, {"lat": 23.25, "lon": 83.0, "u": -0.13, "v": -0.13, "speed": 0.18, "dir": 45.6}, {"lat": 23.25, "lon": 84.25, "u": 0.32, "v": -0.18, "speed": 0.37, "dir": 299.0}, {"lat": 23.25, "lon": 85.5, "u": 0.25, "v": -0.13, "speed": 0.28, "dir": 296.9}, {"lat": 23.25, "lon": 86.75, "u": -0.18, "v": 0.15, "speed": 0.23, "dir": 130.8}, {"lat": 23.25, "lon": 88.0, "u": -0.26, "v": 0.67, "speed": 0.72, "dir": 158.5}, {"lat": 23.25, "lon": 89.25, "u": -0.15, "v": 0.78, "speed": 0.8, "dir": 169.5}, {"lat": 23.25, "lon": 90.5, "u": -0.15, "v": 1.0, "speed": 1.01, "dir": 171.3}, {"lat": 23.25, "lon": 91.75, "u": -0.12, "v": 0.59, "speed": 0.6, "dir": 168.9}, {"lat": 23.25, "lon": 93.0, "u": 0.04, "v": 0.29, "speed": 0.29, "dir": 187.4}, {"lat": 23.25, "lon": 94.25, "u": 0.16, "v": -0.27, "speed": 0.31, "dir": 329.4}, {"lat": 23.25, "lon": 95.5, "u": -0.43, "v": 0.22, "speed": 0.49, "dir": 117.0}, {"lat": 23.25, "lon": 96.75, "u": -0.19, "v": 0.21, "speed": 0.28, "dir": 138.3}, {"lat": 23.25, "lon": 98.0, "u": 0.3, "v": -0.09, "speed": 0.31, "dir": 287.4}, {"lat": 22.0, "lon": 68.0, "u": 2.92, "v": -1.02, "speed": 3.09, "dir": 289.3}, {"lat": 22.0, "lon": 69.25, "u": 2.34, "v": -0.75, "speed": 2.45, "dir": 287.7}, {"lat": 22.0, "lon": 70.5, "u": 1.14, "v": -0.26, "speed": 1.17, "dir": 282.9}, {"lat": 22.0, "lon": 71.75, "u": 1.06, "v": -0.39, "speed": 1.13, "dir": 290.0}, {"lat": 22.0, "lon": 73.0, "u": 0.63, "v": 0.32, "speed": 0.7, "dir": 242.6}, {"lat": 22.0, "lon": 74.25, "u": 0.94, "v": 0.21, "speed": 0.96, "dir": 257.7}, {"lat": 22.0, "lon": 75.5, "u": 1.04, "v": -0.25, "speed": 1.07, "dir": 283.8}, {"lat": 22.0, "lon": 76.75, "u": 0.81, "v": -0.4, "speed": 0.9, "dir": 296.5}, {"lat": 22.0, "lon": 78.0, "u": 0.73, "v": -0.5, "speed": 0.88, "dir": 304.8}, {"lat": 22.0, "lon": 79.25, "u": 0.63, "v": -0.82, "speed": 1.04, "dir": 322.5}, {"lat": 22.0, "lon": 80.5, "u": 0.31, "v": -0.27, "speed": 0.41, "dir": 310.2}, {"lat": 22.0, "lon": 81.75, "u": 0.15, "v": -0.11, "speed": 0.19, "dir": 306.7}, {"lat": 22.0, "lon": 83.0, "u": 0.25, "v": -0.01, "speed": 0.25, "dir": 272.4}, {"lat": 22.0, "lon": 84.25, "u": -0.14, "v": 0.32, "speed": 0.35, "dir": 155.6}, {"lat": 22.0, "lon": 85.5, "u": 0.05, "v": 0.49, "speed": 0.49, "dir": 186.3}, {"lat": 22.0, "lon": 86.75, "u": 0.01, "v": 0.47, "speed": 0.47, "dir": 180.9}, {"lat": 22.0, "lon": 88.0, "u": 0.14, "v": 1.4, "speed": 1.41, "dir": 185.8}, {"lat": 22.0, "lon": 89.25, "u": 0.19, "v": 1.01, "speed": 1.03, "dir": 190.5}, {"lat": 22.0, "lon": 90.5, "u": 0.34, "v": 1.39, "speed": 1.43, "dir": 193.8}, {"lat": 22.0, "lon": 91.75, "u": 0.12, "v": 1.22, "speed": 1.23, "dir": 185.7}, {"lat": 22.0, "lon": 93.0, "u": -0.25, "v": 0.17, "speed": 0.3, "dir": 124.1}, {"lat": 22.0, "lon": 94.25, "u": -0.08, "v": 0.02, "speed": 0.08, "dir": 105.8}, {"lat": 22.0, "lon": 95.5, "u": 0.03, "v": 0.82, "speed": 0.82, "dir": 182.0}, {"lat": 22.0, "lon": 96.75, "u": 0.44, "v": 0.28, "speed": 0.52, "dir": 237.9}, {"lat": 22.0, "lon": 98.0, "u": 0.39, "v": 0.05, "speed": 0.39, "dir": 262.6}, {"lat": 20.75, "lon": 68.0, "u": 2.7, "v": -1.45, "speed": 3.07, "dir": 298.2}, {"lat": 20.75, "lon": 69.25, "u": 2.96, "v": -1.67, "speed": 3.39, "dir": 299.4}, {"lat": 20.75, "lon": 70.5, "u": 2.66, "v": -0.77, "speed": 2.77, "dir": 286.2}, {"lat": 20.75, "lon": 71.75, "u": 2.14, "v": -0.13, "speed": 2.14, "dir": 273.5}, {"lat": 20.75, "lon": 73.0, "u": 1.17, "v": 0.69, "speed": 1.36, "dir": 239.5}, {"lat": 20.75, "lon": 74.25, "u": 1.44, "v": -0.13, "speed": 1.44, "dir": 275.2}, {"lat": 20.75, "lon": 75.5, "u": 1.04, "v": -0.18, "speed": 1.05, "dir": 279.8}, {"lat": 20.75, "lon": 76.75, "u": 1.13, "v": -0.48, "speed": 1.22, "dir": 293.1}, {"lat": 20.75, "lon": 78.0, "u": 0.84, "v": -0.38, "speed": 0.93, "dir": 294.3}, {"lat": 20.75, "lon": 79.25, "u": 0.43, "v": -0.21, "speed": 0.48, "dir": 296.2}, {"lat": 20.75, "lon": 80.5, "u": 0.34, "v": 0.22, "speed": 0.4, "dir": 236.3}, {"lat": 20.75, "lon": 81.75, "u": 0.51, "v": 0.3, "speed": 0.59, "dir": 239.7}, {"lat": 20.75, "lon": 83.0, "u": 0.51, "v": 0.02, "speed": 0.51, "dir": 267.3}, {"lat": 20.75, "lon": 84.25, "u": 0.05, "v": 0.29, "speed": 0.3, "dir": 189.1}, {"lat": 20.75, "lon": 85.5, "u": -0.27, "v": 0.64, "speed": 0.69, "dir": 157.0}, {"lat": 20.75, "lon": 86.75, "u": 0.14, "v": 1.15, "speed": 1.16, "dir": 187.0}, {"lat": 20.75, "lon": 88.0, "u": 0.76, "v": 2.1, "speed": 2.23, "dir": 199.9}, {"lat": 20.75, "lon": 89.25, "u": 0.8, "v": 1.72, "speed": 1.9, "dir": 204.9}, {"lat": 20.75, "lon": 90.5, "u": 0.7, "v": 1.13, "speed": 1.33, "dir": 211.6}, {"lat": 20.75, "lon": 91.75, "u": 0.54, "v": 0.26, "speed": 0.6, "dir": 244.4}, {"lat": 20.75, "lon": 93.0, "u": 0.06, "v": 0.07, "speed": 0.09, "dir": 220.8}, {"lat": 20.75, "lon": 94.25, "u": 0.6, "v": 0.45, "speed": 0.75, "dir": 233.0}, {"lat": 20.75, "lon": 95.5, "u": 0.16, "v": 1.41, "speed": 1.42, "dir": 186.4}, {"lat": 20.75, "lon": 96.75, "u": 0.66, "v": 0.77, "speed": 1.01, "dir": 220.4}, {"lat": 20.75, "lon": 98.0, "u": 0.39, "v": 0.51, "speed": 0.64, "dir": 217.5}, {"lat": 19.5, "lon": 68.0, "u": 2.72, "v": -1.51, "speed": 3.12, "dir": 299.0}, {"lat": 19.5, "lon": 69.25, "u": 2.79, "v": -1.7, "speed": 3.26, "dir": 301.4}, {"lat": 19.5, "lon": 70.5, "u": 2.74, "v": -1.62, "speed": 3.18, "dir": 300.6}, {"lat": 19.5, "lon": 71.75, "u": 2.46, "v": -1.41, "speed": 2.84, "dir": 299.9}, {"lat": 19.5, "lon": 73.0, "u": 0.82, "v": 0.12, "speed": 0.83, "dir": 262.0}, {"lat": 19.5, "lon": 74.25, "u": 1.24, "v": -0.18, "speed": 1.26, "dir": 278.1}, {"lat": 19.5, "lon": 75.5, "u": 0.95, "v": -0.49, "speed": 1.07, "dir": 297.2}, {"lat": 19.5, "lon": 76.75, "u": 0.6, "v": -0.44, "speed": 0.74, "dir": 306.4}, {"lat": 19.5, "lon": 78.0, "u": 0.59, "v": -0.14, "speed": 0.61, "dir": 283.5}, {"lat": 19.5, "lon": 79.25, "u": 0.69, "v": 0.01, "speed": 0.69, "dir": 269.4}, {"lat": 19.5, "lon": 80.5, "u": 0.06, "v": 0.32, "speed": 0.32, "dir": 191.0}, {"lat": 19.5, "lon": 81.75, "u": 0.5, "v": 0.2, "speed": 0.54, "dir": 247.7}, {"lat": 19.5, "lon": 83.0, "u": 0.38, "v": 0.44, "speed": 0.58, "dir": 220.8}, {"lat": 19.5, "lon": 84.25, "u": 0.36, "v": 0.26, "speed": 0.45, "dir": 234.8}, {"lat": 19.5, "lon": 85.5, "u": 0.71, "v": 2.79, "speed": 2.88, "dir": 194.3}, {"lat": 19.5, "lon": 86.75, "u": 0.71, "v": 2.16, "speed": 2.27, "dir": 198.1}, {"lat": 19.5, "lon": 88.0, "u": 0.83, "v": 1.81, "speed": 1.99, "dir": 204.6}, {"lat": 19.5, "lon": 89.25, "u": 0.84, "v": 1.42, "speed": 1.65, "dir": 210.6}, {"lat": 19.5, "lon": 90.5, "u": 0.86, "v": 0.88, "speed": 1.24, "dir": 224.4}, {"lat": 19.5, "lon": 91.75, "u": 1.11, "v": 0.28, "speed": 1.15, "dir": 255.8}, {"lat": 19.5, "lon": 93.0, "u": 1.38, "v": 0.13, "speed": 1.39, "dir": 264.5}, {"lat": 19.5, "lon": 94.25, "u": 0.12, "v": 0.21, "speed": 0.24, "dir": 210.3}, {"lat": 19.5, "lon": 95.5, "u": 0.07, "v": 1.04, "speed": 1.04, "dir": 184.0}, {"lat": 19.5, "lon": 96.75, "u": 0.26, "v": 0.44, "speed": 0.51, "dir": 210.2}, {"lat": 19.5, "lon": 98.0, "u": 0.1, "v": 0.6, "speed": 0.61, "dir": 188.9}, {"lat": 18.25, "lon": 68.0, "u": 2.62, "v": -1.57, "speed": 3.06, "dir": 301.0}, {"lat": 18.25, "lon": 69.25, "u": 2.73, "v": -1.82, "speed": 3.28, "dir": 303.8}, {"lat": 18.25, "lon": 70.5, "u": 2.76, "v": -1.96, "speed": 3.38, "dir": 305.3}, {"lat": 18.25, "lon": 71.75, "u": 2.61, "v": -1.83, "speed": 3.19, "dir": 305.1}, {"lat": 18.25, "lon": 73.0, "u": 1.42, "v": -0.47, "speed": 1.49, "dir": 288.3}, {"lat": 18.25, "lon": 74.25, "u": 1.66, "v": -0.19, "speed": 1.67, "dir": 276.6}, {"lat": 18.25, "lon": 75.5, "u": 0.77, "v": -0.48, "speed": 0.91, "dir": 302.2}, {"lat": 18.25, "lon": 76.75, "u": 0.57, "v": -0.06, "speed": 0.57, "dir": 276.5}, {"lat": 18.25, "lon": 78.0, "u": 0.52, "v": 0.23, "speed": 0.57, "dir": 246.0}, {"lat": 18.25, "lon": 79.25, "u": 0.78, "v": 0.27, "speed": 0.82, "dir": 251.1}, {"lat": 18.25, "lon": 80.5, "u": 0.48, "v": 0.45, "speed": 0.66, "dir": 226.8}, {"lat": 18.25, "lon": 81.75, "u": 0.37, "v": 0.51, "speed": 0.63, "dir": 216.1}, {"lat": 18.25, "lon": 83.0, "u": 0.36, "v": 0.24, "speed": 0.44, "dir": 236.1}, {"lat": 18.25, "lon": 84.25, "u": 0.64, "v": 1.51, "speed": 1.63, "dir": 202.9}, {"lat": 18.25, "lon": 85.5, "u": 0.94, "v": 2.0, "speed": 2.22, "dir": 205.2}, {"lat": 18.25, "lon": 86.75, "u": 0.8, "v": 1.86, "speed": 2.03, "dir": 203.3}, {"lat": 18.25, "lon": 88.0, "u": 0.84, "v": 1.6, "speed": 1.8, "dir": 207.6}, {"lat": 18.25, "lon": 89.25, "u": 0.82, "v": 1.32, "speed": 1.55, "dir": 211.7}, {"lat": 18.25, "lon": 90.5, "u": 0.87, "v": 0.91, "speed": 1.26, "dir": 223.5}, {"lat": 18.25, "lon": 91.75, "u": 1.13, "v": 0.38, "speed": 1.19, "dir": 251.3}, {"lat": 18.25, "lon": 93.0, "u": 1.37, "v": 0.05, "speed": 1.37, "dir": 268.1}, {"lat": 18.25, "lon": 94.25, "u": 0.64, "v": 0.12, "speed": 0.65, "dir": 259.2}, {"lat": 18.25, "lon": 95.5, "u": -0.02, "v": 0.63, "speed": 0.63, "dir": 178.3}, {"lat": 18.25, "lon": 96.75, "u": -0.48, "v": 0.38, "speed": 0.61, "dir": 127.8}, {"lat": 18.25, "lon": 98.0, "u": 0.01, "v": 0.59, "speed": 0.59, "dir": 181.3}, {"lat": 17.0, "lon": 68.0, "u": 2.57, "v": -1.69, "speed": 3.08, "dir": 303.4}, {"lat": 17.0, "lon": 69.25, "u": 2.72, "v": -1.95, "speed": 3.34, "dir": 305.7}, {"lat": 17.0, "lon": 70.5, "u": 2.84, "v": -2.07, "speed": 3.51, "dir": 306.1}, {"lat": 17.0, "lon": 71.75, "u": 2.87, "v": -2.03, "speed": 3.52, "dir": 305.2}, {"lat": 17.0, "lon": 73.0, "u": 2.47, "v": -1.39, "speed": 2.84, "dir": 299.3}, {"lat": 17.0, "lon": 74.25, "u": 1.34, "v": 0.03, "speed": 1.34, "dir": 268.9}, {"lat": 17.0, "lon": 75.5, "u": 1.25, "v": 0.25, "speed": 1.28, "dir": 258.7}, {"lat": 17.0, "lon": 76.75, "u": 0.62, "v": 0.23, "speed": 0.66, "dir": 249.6}, {"lat": 17.0, "lon": 78.0, "u": 0.5, "v": 0.18, "speed": 0.53, "dir": 250.3}, {"lat": 17.0, "lon": 79.25, "u": 0.45, "v": 0.29, "speed": 0.54, "dir": 237.2}, {"lat": 17.0, "lon": 80.5, "u": 0.23, "v": 0.68, "speed": 0.72, "dir": 198.2}, {"lat": 17.0, "lon": 81.75, "u": 0.04, "v": 0.49, "speed": 0.49, "dir": 184.6}, {"lat": 17.0, "lon": 83.0, "u": 0.65, "v": 1.56, "speed": 1.69, "dir": 202.6}, {"lat": 17.0, "lon": 84.25, "u": 0.77, "v": 1.67, "speed": 1.84, "dir": 204.8}, {"lat": 17.0, "lon": 85.5, "u": 0.72, "v": 1.68, "speed": 1.83, "dir": 203.1}, {"lat": 17.0, "lon": 86.75, "u": 0.67, "v": 1.58, "speed": 1.72, "dir": 203.0}, {"lat": 17.0, "lon": 88.0, "u": 0.63, "v": 1.44, "speed": 1.58, "dir": 203.7}, {"lat": 17.0, "lon": 89.25, "u": 0.63, "v": 1.23, "speed": 1.39, "dir": 207.1}, {"lat": 17.0, "lon": 90.5, "u": 0.72, "v": 0.89, "speed": 1.14, "dir": 219.0}, {"lat": 17.0, "lon": 91.75, "u": 0.88, "v": 0.48, "speed": 1.0, "dir": 241.3}, {"lat": 17.0, "lon": 93.0, "u": 1.13, "v": 0.12, "speed": 1.14, "dir": 264.0}, {"lat": 17.0, "lon": 94.25, "u": 1.33, "v": -0.22, "speed": 1.34, "dir": 279.3}, {"lat": 17.0, "lon": 95.5, "u": 0.61, "v": 0.43, "speed": 0.75, "dir": 234.9}, {"lat": 17.0, "lon": 96.75, "u": 0.16, "v": 0.98, "speed": 1.0, "dir": 189.2}, {"lat": 17.0, "lon": 98.0, "u": -0.16, "v": 0.29, "speed": 0.33, "dir": 151.7}, {"lat": 15.75, "lon": 68.0, "u": 2.51, "v": -1.76, "speed": 3.07, "dir": 305.1}, {"lat": 15.75, "lon": 69.25, "u": 2.69, "v": -1.98, "speed": 3.34, "dir": 306.4}, {"lat": 15.75, "lon": 70.5, "u": 2.78, "v": -2.1, "speed": 3.49, "dir": 307.0}, {"lat": 15.75, "lon": 71.75, "u": 2.88, "v": -2.05, "speed": 3.53, "dir": 305.4}, {"lat": 15.75, "lon": 73.0, "u": 2.91, "v": -1.75, "speed": 3.4, "dir": 301.1}, {"lat": 15.75, "lon": 74.25, "u": 0.85, "v": 0.19, "speed": 0.88, "dir": 257.3}, {"lat": 15.75, "lon": 75.5, "u": 1.05, "v": 0.31, "speed": 1.1, "dir": 253.8}, {"lat": 15.75, "lon": 76.75, "u": 0.95, "v": 0.19, "speed": 0.96, "dir": 258.6}, {"lat": 15.75, "lon": 78.0, "u": 0.63, "v": 0.12, "speed": 0.64, "dir": 259.2}, {"lat": 15.75, "lon": 79.25, "u": 0.54, "v": 0.19, "speed": 0.57, "dir": 250.4}, {"lat": 15.75, "lon": 80.5, "u": 0.08, "v": 1.37, "speed": 1.37, "dir": 183.6}, {"lat": 15.75, "lon": 81.75, "u": 0.06, "v": 1.72, "speed": 1.72, "dir": 181.9}, {"lat": 15.75, "lon": 83.0, "u": 0.31, "v": 1.47, "speed": 1.51, "dir": 192.1}, {"lat": 15.75, "lon": 84.25, "u": 0.41, "v": 1.43, "speed": 1.49, "dir": 196.2}, {"lat": 15.75, "lon": 85.5, "u": 0.43, "v": 1.45, "speed": 1.51, "dir": 196.4}, {"lat": 15.75, "lon": 86.75, "u": 0.42, "v": 1.4, "speed": 1.46, "dir": 196.7}, {"lat": 15.75, "lon": 88.0, "u": 0.38, "v": 1.3, "speed": 1.36, "dir": 196.3}, {"lat": 15.75, "lon": 89.25, "u": 0.35, "v": 1.15, "speed": 1.2, "dir": 197.2}, {"lat": 15.75, "lon": 90.5, "u": 0.45, "v": 0.9, "speed": 1.0, "dir": 206.4}, {"lat": 15.75, "lon": 91.75, "u": 0.59, "v": 0.64, "speed": 0.87, "dir": 222.4}, {"lat": 15.75, "lon": 93.0, "u": 0.88, "v": 0.35, "speed": 0.95, "dir": 248.2}, {"lat": 15.75, "lon": 94.25, "u": 1.37, "v": 0.48, "speed": 1.45, "dir": 250.6}, {"lat": 15.75, "lon": 95.5, "u": 1.12, "v": 0.92, "speed": 1.45, "dir": 230.5}, {"lat": 15.75, "lon": 96.75, "u": 1.3, "v": 0.94, "speed": 1.6, "dir": 234.2}, {"lat": 15.75, "lon": 98.0, "u": 0.01, "v": 0.6, "speed": 0.6, "dir": 180.9}, {"lat": 14.5, "lon": 68.0, "u": 2.47, "v": -1.78, "speed": 3.05, "dir": 305.8}, {"lat": 14.5, "lon": 69.25, "u": 2.61, "v": -1.97, "speed": 3.27, "dir": 307.1}, {"lat": 14.5, "lon": 70.5, "u": 2.74, "v": -2.07, "speed": 3.43, "dir": 307.2}, {"lat": 14.5, "lon": 71.75, "u": 2.84, "v": -2.05, "speed": 3.5, "dir": 305.8}, {"lat": 14.5, "lon": 73.0, "u": 2.84, "v": -1.82, "speed": 3.38, "dir": 302.6}, {"lat": 14.5, "lon": 74.25, "u": 1.9, "v": -0.68, "speed": 2.02, "dir": 289.7}, {"lat": 14.5, "lon": 75.5, "u": 1.13, "v": 0.19, "speed": 1.15, "dir": 260.6}, {"lat": 14.5, "lon": 76.75, "u": 1.07, "v": 0.03, "speed": 1.07, "dir": 268.5}, {"lat": 14.5, "lon": 78.0, "u": 0.69, "v": 0.21, "speed": 0.73, "dir": 253.0}, {"lat": 14.5, "lon": 79.25, "u": 0.4, "v": 0.02, "speed": 0.4, "dir": 266.8}, {"lat": 14.5, "lon": 80.5, "u": -0.56, "v": 1.24, "speed": 1.36, "dir": 155.6}, {"lat": 14.5, "lon": 81.75, "u": -0.1, "v": 1.33, "speed": 1.34, "dir": 175.5}, {"lat": 14.5, "lon": 83.0, "u": 0.11, "v": 1.27, "speed": 1.28, "dir": 184.9}, {"lat": 14.5, "lon": 84.25, "u": 0.14, "v": 1.31, "speed": 1.32, "dir": 186.1}, {"lat": 14.5, "lon": 85.5, "u": 0.16, "v": 1.34, "speed": 1.35, "dir": 186.9}, {"lat": 14.5, "lon": 86.75, "u": 0.18, "v": 1.32, "speed": 1.34, "dir": 187.6}, {"lat": 14.5, "lon": 88.0, "u": 0.17, "v": 1.25, "speed": 1.26, "dir": 187.6}, {"lat": 14.5, "lon": 89.25, "u": 0.15, "v": 1.12, "speed": 1.13, "dir": 187.6}, {"lat": 14.5, "lon": 90.5, "u": 0.23, "v": 0.96, "speed": 0.99, "dir": 193.2}, {"lat": 14.5, "lon": 91.75, "u": 0.34, "v": 0.82, "speed": 0.89, "dir": 202.8}, {"lat": 14.5, "lon": 93.0, "u": 0.56, "v": 0.67, "speed": 0.87, "dir": 220.3}, {"lat": 14.5, "lon": 94.25, "u": 0.87, "v": 0.67, "speed": 1.09, "dir": 232.4}, {"lat": 14.5, "lon": 95.5, "u": 1.0, "v": 0.76, "speed": 1.25, "dir": 232.7}, {"lat": 14.5, "lon": 96.75, "u": 0.96, "v": 0.63, "speed": 1.15, "dir": 236.8}, {"lat": 14.5, "lon": 98.0, "u": 0.09, "v": 0.35, "speed": 0.36, "dir": 194.0}, {"lat": 13.25, "lon": 68.0, "u": 2.45, "v": -1.73, "speed": 3.0, "dir": 305.3}, {"lat": 13.25, "lon": 69.25, "u": 2.56, "v": -1.9, "speed": 3.19, "dir": 306.6}, {"lat": 13.25, "lon": 70.5, "u": 2.71, "v": -2.01, "speed": 3.37, "dir": 306.6}, {"lat": 13.25, "lon": 71.75, "u": 2.8, "v": -1.98, "speed": 3.43, "dir": 305.3}, {"lat": 13.25, "lon": 73.0, "u": 2.8, "v": -1.78, "speed": 3.31, "dir": 302.5}, {"lat": 13.25, "lon": 74.25, "u": 2.52, "v": -1.28, "speed": 2.82, "dir": 296.9}, {"lat": 13.25, "lon": 75.5, "u": 0.44, "v": 0.14, "speed": 0.46, "dir": 252.4}, {"lat": 13.25, "lon": 76.75, "u": 0.6, "v": -0.09, "speed": 0.61, "dir": 278.8}, {"lat": 13.25, "lon": 78.0, "u": 0.65, "v": -0.13, "speed": 0.67, "dir": 281.4}, {"lat": 13.25, "lon": 79.25, "u": 0.36, "v": -0.23, "speed": 0.43, "dir": 303.0}, {"lat": 13.25, "lon": 80.5, "u": -0.64, "v": 1.03, "speed": 1.21, "dir": 148.3}, {"lat": 13.25, "lon": 81.75, "u": -0.13, "v": 1.25, "speed": 1.26, "dir": 174.0}, {"lat": 13.25, "lon": 83.0, "u": 0.05, "v": 1.21, "speed": 1.21, "dir": 182.6}, {"lat": 13.25, "lon": 84.25, "u": 0.09, "v": 1.21, "speed": 1.21, "dir": 184.3}, {"lat": 13.25, "lon": 85.5, "u": 0.08, "v": 1.22, "speed": 1.22, "dir": 183.7}, {"lat": 13.25, "lon": 86.75, "u": 0.05, "v": 1.27, "speed": 1.27, "dir": 182.2}, {"lat": 13.25, "lon": 88.0, "u": 0.05, "v": 1.27, "speed": 1.27, "dir": 182.1}, {"lat": 13.25, "lon": 89.25, "u": 0.04, "v": 1.17, "speed": 1.18, "dir": 182.0}, {"lat": 13.25, "lon": 90.5, "u": 0.07, "v": 1.06, "speed": 1.06, "dir": 183.8}, {"lat": 13.25, "lon": 91.75, "u": 0.19, "v": 0.95, "speed": 0.97, "dir": 191.1}, {"lat": 13.25, "lon": 93.0, "u": 0.27, "v": 0.85, "speed": 0.89, "dir": 197.3}, {"lat": 13.25, "lon": 94.25, "u": 0.45, "v": 0.9, "speed": 1.01, "dir": 206.3}, {"lat": 13.25, "lon": 95.5, "u": 0.65, "v": 0.83, "speed": 1.05, "dir": 218.2}, {"lat": 13.25, "lon": 96.75, "u": 0.81, "v": 0.58, "speed": 0.99, "dir": 234.5}, {"lat": 13.25, "lon": 98.0, "u": 0.84, "v": 0.03, "speed": 0.84, "dir": 267.7}, {"lat": 12.0, "lon": 68.0, "u": 2.45, "v": -1.72, "speed": 2.99, "dir": 305.0}, {"lat": 12.0, "lon": 69.25, "u": 2.62, "v": -1.84, "speed": 3.2, "dir": 305.2}, {"lat": 12.0, "lon": 70.5, "u": 2.76, "v": -1.93, "speed": 3.37, "dir": 305.0}, {"lat": 12.0, "lon": 71.75, "u": 2.91, "v": -1.91, "speed": 3.48, "dir": 303.3}, {"lat": 12.0, "lon": 73.0, "u": 2.97, "v": -1.73, "speed": 3.43, "dir": 300.3}, {"lat": 12.0, "lon": 74.25, "u": 2.62, "v": -1.53, "speed": 3.04, "dir": 300.2}, {"lat": 12.0, "lon": 75.5, "u": 0.62, "v": -0.33, "speed": 0.7, "dir": 298.1}, {"lat": 12.0, "lon": 76.75, "u": 0.79, "v": 0.2, "speed": 0.82, "dir": 255.9}, {"lat": 12.0, "lon": 78.0, "u": 0.25, "v": -0.23, "speed": 0.33, "dir": 312.6}, {"lat": 12.0, "lon": 79.25, "u": 0.33, "v": -0.17, "speed": 0.37, "dir": 296.7}, {"lat": 12.0, "lon": 80.5, "u": -0.16, "v": 1.09, "speed": 1.1, "dir": 171.8}, {"lat": 12.0, "lon": 81.75, "u": 0.21, "v": 1.17, "speed": 1.18, "dir": 190.3}, {"lat": 12.0, "lon": 83.0, "u": 0.27, "v": 1.07, "speed": 1.11, "dir": 194.0}, {"lat": 12.0, "lon": 84.25, "u": 0.17, "v": 1.11, "speed": 1.12, "dir": 189.0}, {"lat": 12.0, "lon": 85.5, "u": 0.1, "v": 1.22, "speed": 1.22, "dir": 184.9}, {"lat": 12.0, "lon": 86.75, "u": 0.08, "v": 1.3, "speed": 1.3, "dir": 183.4}, {"lat": 12.0, "lon": 88.0, "u": 0.05, "v": 1.31, "speed": 1.31, "dir": 182.4}, {"lat": 12.0, "lon": 89.25, "u": 0.03, "v": 1.28, "speed": 1.28, "dir": 181.4}, {"lat": 12.0, "lon": 90.5, "u": 0.07, "v": 1.23, "speed": 1.23, "dir": 183.1}, {"lat": 12.0, "lon": 91.75, "u": 0.19, "v": 1.2, "speed": 1.21, "dir": 189.1}, {"lat": 12.0, "lon": 93.0, "u": 0.2, "v": 1.14, "speed": 1.16, "dir": 190.0}, {"lat": 12.0, "lon": 94.25, "u": 0.36, "v": 1.14, "speed": 1.19, "dir": 197.7}, {"lat": 12.0, "lon": 95.5, "u": 0.47, "v": 0.98, "speed": 1.08, "dir": 205.7}, {"lat": 12.0, "lon": 96.75, "u": 0.58, "v": 0.7, "speed": 0.91, "dir": 219.5}, {"lat": 12.0, "lon": 98.0, "u": 0.92, "v": 0.24, "speed": 0.95, "dir": 255.5}, {"lat": 10.75, "lon": 68.0, "u": 2.49, "v": -1.68, "speed": 3.0, "dir": 304.0}, {"lat": 10.75, "lon": 69.25, "u": 2.66, "v": -1.79, "speed": 3.21, "dir": 304.0}, {"lat": 10.75, "lon": 70.5, "u": 2.78, "v": -1.86, "speed": 3.34, "dir": 303.7}, {"lat": 10.75, "lon": 71.75, "u": 2.95, "v": -1.8, "speed": 3.45, "dir": 301.4}, {"lat": 10.75, "lon": 73.0, "u": 3.06, "v": -1.73, "speed": 3.51, "dir": 299.5}, {"lat": 10.75, "lon": 74.25, "u": 2.89, "v": -1.71, "speed": 3.35, "dir": 300.6}, {"lat": 10.75, "lon": 75.5, "u": 2.47, "v": -1.62, "speed": 2.96, "dir": 303.3}, {"lat": 10.75, "lon": 76.75, "u": 0.68, "v": 0.5, "speed": 0.84, "dir": 233.6}, {"lat": 10.75, "lon": 78.0, "u": 0.9, "v": -0.12, "speed": 0.9, "dir": 277.9}, {"lat": 10.75, "lon": 79.25, "u": 0.48, "v": -0.13, "speed": 0.5, "dir": 285.0}, {"lat": 10.75, "lon": 80.5, "u": 0.53, "v": 1.26, "speed": 1.37, "dir": 202.9}, {"lat": 10.75, "lon": 81.75, "u": 0.79, "v": 0.92, "speed": 1.21, "dir": 220.4}, {"lat": 10.75, "lon": 83.0, "u": 0.64, "v": 0.87, "speed": 1.08, "dir": 216.3}, {"lat": 10.75, "lon": 84.25, "u": 0.46, "v": 1.05, "speed": 1.15, "dir": 203.7}, {"lat": 10.75, "lon": 85.5, "u": 0.32, "v": 1.27, "speed": 1.31, "dir": 194.0}, {"lat": 10.75, "lon": 86.75, "u": 0.28, "v": 1.42, "speed": 1.45, "dir": 191.2}, {"lat": 10.75, "lon": 88.0, "u": 0.28, "v": 1.5, "speed": 1.52, "dir": 190.7}, {"lat": 10.75, "lon": 89.25, "u": 0.3, "v": 1.47, "speed": 1.5, "dir": 191.5}, {"lat": 10.75, "lon": 90.5, "u": 0.28, "v": 1.47, "speed": 1.49, "dir": 191.0}, {"lat": 10.75, "lon": 91.75, "u": 0.27, "v": 1.46, "speed": 1.48, "dir": 190.5}, {"lat": 10.75, "lon": 93.0, "u": 0.34, "v": 1.41, "speed": 1.45, "dir": 193.4}, {"lat": 10.75, "lon": 94.25, "u": 0.41, "v": 1.32, "speed": 1.39, "dir": 197.3}, {"lat": 10.75, "lon": 95.5, "u": 0.5, "v": 1.09, "speed": 1.2, "dir": 204.7}, {"lat": 10.75, "lon": 96.75, "u": 0.5, "v": 0.73, "speed": 0.89, "dir": 214.2}, {"lat": 10.75, "lon": 98.0, "u": 0.59, "v": 0.5, "speed": 0.77, "dir": 229.3}, {"lat": 9.5, "lon": 68.0, "u": 2.43, "v": -1.59, "speed": 2.9, "dir": 303.1}, {"lat": 9.5, "lon": 69.25, "u": 2.59, "v": -1.68, "speed": 3.08, "dir": 303.0}, {"lat": 9.5, "lon": 70.5, "u": 2.76, "v": -1.7, "speed": 3.24, "dir": 301.6}, {"lat": 9.5, "lon": 71.75, "u": 2.92, "v": -1.72, "speed": 3.39, "dir": 300.5}, {"lat": 9.5, "lon": 73.0, "u": 3.06, "v": -1.71, "speed": 3.5, "dir": 299.2}, {"lat": 9.5, "lon": 74.25, "u": 3.14, "v": -1.79, "speed": 3.62, "dir": 299.6}, {"lat": 9.5, "lon": 75.5, "u": 2.9, "v": -1.71, "speed": 3.37, "dir": 300.5}, {"lat": 9.5, "lon": 76.75, "u": 0.48, "v": -0.69, "speed": 0.84, "dir": 325.0}, {"lat": 9.5, "lon": 78.0, "u": -0.04, "v": -0.1, "speed": 0.11, "dir": 22.7}, {"lat": 9.5, "lon": 79.25, "u": 0.09, "v": 1.14, "speed": 1.15, "dir": 184.3}, {"lat": 9.5, "lon": 80.5, "u": 0.86, "v": 0.91, "speed": 1.25, "dir": 223.4}, {"lat": 9.5, "lon": 81.75, "u": 1.26, "v": 0.66, "speed": 1.42, "dir": 242.3}, {"lat": 9.5, "lon": 83.0, "u": 0.98, "v": 0.62, "speed": 1.16, "dir": 237.9}, {"lat": 9.5, "lon": 84.25, "u": 0.71, "v": 0.99, "speed": 1.22, "dir": 215.7}, {"lat": 9.5, "lon": 85.5, "u": 0.69, "v": 1.39, "speed": 1.55, "dir": 206.4}, {"lat": 9.5, "lon": 86.75, "u": 0.75, "v": 1.63, "speed": 1.79, "dir": 204.7}, {"lat": 9.5, "lon": 88.0, "u": 0.76, "v": 1.7, "speed": 1.86, "dir": 204.1}, {"lat": 9.5, "lon": 89.25, "u": 0.74, "v": 1.69, "speed": 1.84, "dir": 203.6}, {"lat": 9.5, "lon": 90.5, "u": 0.69, "v": 1.67, "speed": 1.8, "dir": 202.5}, {"lat": 9.5, "lon": 91.75, "u": 0.65, "v": 1.68, "speed": 1.8, "dir": 201.2}, {"lat": 9.5, "lon": 93.0, "u": 0.62, "v": 1.66, "speed": 1.77, "dir": 200.5}, {"lat": 9.5, "lon": 94.25, "u": 0.67, "v": 1.53, "speed": 1.67, "dir": 203.7}, {"lat": 9.5, "lon": 95.5, "u": 0.78, "v": 1.22, "speed": 1.44, "dir": 212.5}, {"lat": 9.5, "lon": 96.75, "u": 0.84, "v": 0.69, "speed": 1.09, "dir": 230.2}, {"lat": 9.5, "lon": 98.0, "u": 0.77, "v": 0.26, "speed": 0.81, "dir": 251.1}, {"lat": 8.25, "lon": 68.0, "u": 2.32, "v": -1.41, "speed": 2.72, "dir": 301.3}, {"lat": 8.25, "lon": 69.25, "u": 2.46, "v": -1.49, "speed": 2.87, "dir": 301.1}, {"lat": 8.25, "lon": 70.5, "u": 2.64, "v": -1.54, "speed": 3.06, "dir": 300.2}, {"lat": 8.25, "lon": 71.75, "u": 2.86, "v": -1.56, "speed": 3.26, "dir": 298.6}, {"lat": 8.25, "lon": 73.0, "u": 3.09, "v": -1.57, "speed": 3.47, "dir": 297.0}, {"lat": 8.25, "lon": 74.25, "u": 3.31, "v": -1.58, "speed": 3.67, "dir": 295.4}, {"lat": 8.25, "lon": 75.5, "u": 3.4, "v": -1.61, "speed": 3.76, "dir": 295.4}, {"lat": 8.25, "lon": 76.75, "u": 3.34, "v": -2.05, "speed": 3.92, "dir": 301.5}, {"lat": 8.25, "lon": 78.0, "u": 2.12, "v": 0.28, "speed": 2.13, "dir": 262.4}, {"lat": 8.25, "lon": 79.25, "u": 2.27, "v": 1.2, "speed": 2.57, "dir": 242.1}, {"lat": 8.25, "lon": 80.5, "u": 1.33, "v": 1.24, "speed": 1.82, "dir": 227.0}, {"lat": 8.25, "lon": 81.75, "u": 1.29, "v": -0.08, "speed": 1.29, "dir": 273.3}, {"lat": 8.25, "lon": 83.0, "u": 0.73, "v": 0.49, "speed": 0.88, "dir": 236.0}, {"lat": 8.25, "lon": 84.25, "u": 1.23, "v": 1.23, "speed": 1.74, "dir": 225.0}, {"lat": 8.25, "lon": 85.5, "u": 1.54, "v": 1.65, "speed": 2.26, "dir": 223.0}, {"lat": 8.25, "lon": 86.75, "u": 1.55, "v": 1.81, "speed": 2.39, "dir": 220.6}, {"lat": 8.25, "lon": 88.0, "u": 1.47, "v": 1.84, "speed": 2.35, "dir": 218.6}, {"lat": 8.25, "lon": 89.25, "u": 1.36, "v": 1.83, "speed": 2.28, "dir": 216.7}, {"lat": 8.25, "lon": 90.5, "u": 1.22, "v": 1.82, "speed": 2.19, "dir": 213.8}, {"lat": 8.25, "lon": 91.75, "u": 1.05, "v": 1.78, "speed": 2.07, "dir": 210.5}, {"lat": 8.25, "lon": 93.0, "u": 0.9, "v": 1.82, "speed": 2.03, "dir": 206.4}, {"lat": 8.25, "lon": 94.25, "u": 0.94, "v": 1.78, "speed": 2.02, "dir": 207.9}, {"lat": 8.25, "lon": 95.5, "u": 1.1, "v": 1.42, "speed": 1.8, "dir": 217.8}, {"lat": 8.25, "lon": 96.75, "u": 1.23, "v": 0.76, "speed": 1.44, "dir": 238.2}, {"lat": 8.25, "lon": 98.0, "u": 1.0, "v": -0.06, "speed": 1.01, "dir": 273.2}, {"lat": 7.0, "lon": 68.0, "u": 2.34, "v": -1.18, "speed": 2.62, "dir": 296.8}, {"lat": 7.0, "lon": 69.25, "u": 2.46, "v": -1.27, "speed": 2.77, "dir": 297.3}, {"lat": 7.0, "lon": 70.5, "u": 2.63, "v": -1.31, "speed": 2.93, "dir": 296.5}, {"lat": 7.0, "lon": 71.75, "u": 2.82, "v": -1.29, "speed": 3.1, "dir": 294.7}, {"lat": 7.0, "lon": 73.0, "u": 3.04, "v": -1.25, "speed": 3.29, "dir": 292.4}, {"lat": 7.0, "lon": 74.25, "u": 3.24, "v": -1.25, "speed": 3.47, "dir": 291.0}, {"lat": 7.0, "lon": 75.5, "u": 3.27, "v": -1.31, "speed": 3.53, "dir": 291.8}, {"lat": 7.0, "lon": 76.75, "u": 3.02, "v": -1.81, "speed": 3.52, "dir": 300.8}, {"lat": 7.0, "lon": 78.0, "u": 3.62, "v": -1.7, "speed": 4.0, "dir": 295.2}, {"lat": 7.0, "lon": 79.25, "u": 3.56, "v": -0.46, "speed": 3.59, "dir": 277.4}, {"lat": 7.0, "lon": 80.5, "u": 0.49, "v": 0.16, "speed": 0.52, "dir": 251.9}, {"lat": 7.0, "lon": 81.75, "u": 0.66, "v": 0.32, "speed": 0.73, "dir": 244.4}, {"lat": 7.0, "lon": 83.0, "u": 2.32, "v": 1.5, "speed": 2.77, "dir": 237.2}, {"lat": 7.0, "lon": 84.25, "u": 2.66, "v": 1.59, "speed": 3.1, "dir": 239.1}, {"lat": 7.0, "lon": 85.5, "u": 2.65, "v": 1.75, "speed": 3.17, "dir": 236.6}, {"lat": 7.0, "lon": 86.75, "u": 2.47, "v": 1.84, "speed": 3.08, "dir": 233.2}, {"lat": 7.0, "lon": 88.0, "u": 2.24, "v": 1.85, "speed": 2.91, "dir": 230.5}, {"lat": 7.0, "lon": 89.25, "u": 2.0, "v": 1.78, "speed": 2.68, "dir": 228.4}, {"lat": 7.0, "lon": 90.5, "u": 1.74, "v": 1.74, "speed": 2.46, "dir": 225.1}, {"lat": 7.0, "lon": 91.75, "u": 1.43, "v": 1.74, "speed": 2.25, "dir": 219.4}, {"lat": 7.0, "lon": 93.0, "u": 1.11, "v": 1.82, "speed": 2.13, "dir": 211.5}, {"lat": 7.0, "lon": 94.25, "u": 0.99, "v": 2.02, "speed": 2.25, "dir": 206.1}, {"lat": 7.0, "lon": 95.5, "u": 1.33, "v": 1.64, "speed": 2.11, "dir": 219.0}, {"lat": 7.0, "lon": 96.75, "u": 1.07, "v": 0.35, "speed": 1.13, "dir": 251.7}, {"lat": 7.0, "lon": 98.0, "u": 0.46, "v": -0.59, "speed": 0.74, "dir": 322.0}]}